rabo_dev_kit/__init__.py
rabo_dev_kit/recorder.cpython-312-x86_64-linux-gnu.so
rabo_dev_kit/remote_control.py
rabo_dev_kit/sync_bridge.cpython-312-x86_64-linux-gnu.so
rabo_dev_kit/utils.cpython-312-x86_64-linux-gnu.so
rabo_dev_kit-0.1.10.dist-info/METADATA
rabo_dev_kit-0.1.10.dist-info/WHEEL
rabo_dev_kit-0.1.10.dist-info/top_level.txt
rabo_dev_kit-0.1.10.dist-info/RECORD
