Metadata-Version: 2.1
Name: rabo-dev-kit
Version: 0.1.10
Summary: A ROS2 development toolkit for data recording, topic synchronization and utilities
Home-page: 
Author: origin
Author-email: origin <cmeng.gao@gmail.com>
License: MIT
Keywords: ros2,robotics,development,toolkit,synchronization
Classifier: Programming Language :: Python :: 3
Classifier: Programming Language :: Python :: 3.6
Classifier: Programming Language :: Python :: 3.7
Classifier: Programming Language :: Python :: 3.8
Classifier: Programming Language :: Python :: 3.9
Classifier: Programming Language :: Python :: 3.10
Classifier: License :: OSI Approved :: MIT License
Classifier: Operating System :: OS Independent
Classifier: Topic :: Software Development :: Libraries :: Python Modules
Classifier: Intended Audience :: Developers
Requires-Python: >=3.6
Provides-Extra: ros2
Requires-Dist: rclpy; extra == "ros2"
